{
    "data": [
        {
            "locale": "zh-rCN",
            "data": {
                "label": "Log4a",
                "dev_team": "pqpo",
                "rule_contributors": [
                    "crrashh1542"
                ],
                "description": "Log4a 是一个基于 mmap，高性能、高可用的 Android 日志收集框架。",
                "source_link": "https://github.com/pqpo/Log4a"
            }
        },
        {
            "locale": "en",
            "data": {
                "label": "Log4a",
                "dev_team": "pqpo",
                "rule_contributors": [
                    "crrashh1542"
                ],
                "description": "Log4a 是一个基于 mmap，高性能、高可用的 Android 日志收集框架。",
                "source_link": "https://github.com/pqpo/Log4a"
            }
        }
    ],
    "uuid": "96C62FC5-DBC7-4E41-B755-21790B6C3C4A"
}